{"dependencies":[{"name":"C:\\Users\\39351\\Progetti\\Node\\SolidTest\\package.json","includedInParent":true,"mtime":1670177358204},{"name":"C:\\Users\\39351\\Progetti\\Node\\SolidTest\\node_modules\\stream-browserify\\node_modules\\readable-stream\\package.json","includedInParent":true,"mtime":1670176740137},{"name":"./lib/_stream_writable.js","loc":{"line":1,"column":25}}],"generated":{"js":"module.exports = require('./lib/_stream_writable.js');\n","map":{"mappings":[{"source":"node_modules\\stream-browserify\\node_modules\\readable-stream\\writable-browser.js","original":{"line":1,"column":0},"generated":{"line":1,"column":0}},{"source":"node_modules\\stream-browserify\\node_modules\\readable-stream\\writable-browser.js","original":{"line":2,"column":0},"generated":{"line":2,"column":0}}],"sources":{"node_modules\\stream-browserify\\node_modules\\readable-stream\\writable-browser.js":"module.exports = require('./lib/_stream_writable.js');\n"},"lineCount":2}},"hash":"bbffac5431cf1230f23e4148e53df251","cacheData":{"env":{}}}